{
  "continent": "asia",
  "country": "taiwan",
  "city": "taipei",
  "aliases": ["taipei", "타이베이"],
  "default_days": 3,
  "places": [
    {
      "id": "taipei-101",
      "name": "타이베이 101",
      "category": ["sightseeing", "photo", "shopping"],
      "budget_level": ["medium", "high"],
      "suitable_for": ["solo", "couple", "friend", "family"],
      "time_fit": ["afternoon", "evening"],
      "area": "신이",
      "duration_hours": 3,
      "priority": 10,
      "pace": ["easy"],
      "mobility": ["subway-friendly", "walkable"],
      "summary": "타이베이를 대표하는 랜드마크로 쇼핑과 야경을 묶기 좋다."
    },
    {
      "id": "elephant-mountain",
      "name": "샹산(코끼리산)",
      "category": ["nature", "photo", "activity"],
      "budget_level": ["low", "medium"],
      "suitable_for": ["solo", "couple", "friend"],
      "time_fit": ["afternoon", "evening"],
      "area": "신이",
      "duration_hours": 2,
      "priority": 8,
      "pace": ["tight"],
      "mobility": ["walkable", "subway-friendly"],
      "summary": "타이베이 101 야경을 보기 좋은 대표 전망 코스다."
    },
    {
      "id": "chiang-kai-shek",
      "name": "중정기념당",
      "category": ["culture", "sightseeing", "photo"],
      "budget_level": ["low", "medium", "high"],
      "suitable_for": ["solo", "couple", "friend", "family"],
      "time_fit": ["morning", "afternoon"],
      "area": "중정",
      "duration_hours": 2,
      "priority": 9,
      "pace": ["easy"],
      "mobility": ["walkable", "subway-friendly"],
      "summary": "넓은 광장과 건축물 덕분에 관광형 일정의 중심으로 안정적이다."
    },
    {
      "id": "yongkang-street",
      "name": "융캉제",
      "category": ["food", "shopping", "culture"],
      "budget_level": ["low", "medium", "high"],
      "suitable_for": ["solo", "couple", "friend"],
      "time_fit": ["afternoon", "evening"],
      "area": "다안",
      "duration_hours": 2,
      "priority": 8,
      "pace": ["easy"],
      "mobility": ["walkable"],
      "summary": "맛집과 디저트, 골목 분위기를 함께 즐기기 좋은 타이베이 대표 거리다."
    },
    {
      "id": "daan-park",
      "name": "다안삼림공원",
      "category": ["relax", "nature", "photo"],
      "budget_level": ["low", "medium", "high"],
      "suitable_for": ["solo", "couple", "friend", "family"],
      "time_fit": ["morning"],
      "area": "다안",
      "duration_hours": 2,
      "priority": 7,
      "pace": ["easy"],
      "mobility": ["walkable", "subway-friendly"],
      "summary": "도심에서 가볍게 산책하며 하루를 시작하기 좋은 공원이다."
    },
    {
      "id": "ximending",
      "name": "시먼딩",
      "category": ["shopping", "food", "nightlife"],
      "budget_level": ["low", "medium"],
      "suitable_for": ["solo", "friend", "couple"],
      "time_fit": ["afternoon", "evening"],
      "area": "완화",
      "duration_hours": 3,
      "priority": 9,
      "pace": ["tight", "easy"],
      "mobility": ["walkable", "subway-friendly"],
      "summary": "활기 있는 쇼핑과 길거리 음식이 강한 타이베이 도심 지역이다."
    },
    {
      "id": "longshan",
      "name": "용산사",
      "category": ["culture", "sightseeing", "relax"],
      "budget_level": ["low", "medium", "high"],
      "suitable_for": ["solo", "couple", "friend", "family"],
      "time_fit": ["morning", "afternoon"],
      "area": "완화",
      "duration_hours": 1,
      "priority": 8,
      "pace": ["easy"],
      "mobility": ["walkable", "subway-friendly"],
      "summary": "시먼딩과 함께 묶기 좋고 타이베이 전통 분위기를 느끼기 좋다."
    },
    {
      "id": "raohe-night-market",
      "name": "라오허 야시장",
      "category": ["food", "shopping", "nightlife"],
      "budget_level": ["low", "medium"],
      "suitable_for": ["friend", "solo", "couple", "family"],
      "time_fit": ["evening"],
      "area": "송산",
      "duration_hours": 2,
      "priority": 9,
      "pace": ["easy"],
      "mobility": ["walkable"],
      "summary": "야시장 음식 중심 일정에 가장 잘 어울리는 저녁 코스 중 하나다."
    },
    {
      "id": "songshan-cultural",
      "name": "송산문창원구",
      "category": ["culture", "shopping", "photo"],
      "budget_level": ["medium", "high"],
      "suitable_for": ["solo", "couple", "friend"],
      "time_fit": ["afternoon"],
      "area": "송산",
      "duration_hours": 2,
      "priority": 7,
      "pace": ["easy"],
      "mobility": ["walkable", "subway-friendly"],
      "summary": "디자인 상점과 전시가 있어 감성적인 도심 코스로 쓰기 좋다."
    },
    {
      "id": "beitou-hot-spring",
      "name": "베이터우 온천지구",
      "category": ["relax", "culture", "nature"],
      "budget_level": ["medium", "high"],
      "suitable_for": ["couple", "family", "solo", "friend"],
      "time_fit": ["afternoon", "evening"],
      "area": "베이터우",
      "duration_hours": 3,
      "priority": 8,
      "pace": ["easy"],
      "mobility": ["subway-friendly"],
      "summary": "도심 여행에 여유를 더해주는 타이베이 대표 힐링 코스다."
    },
    {
      "id": "national-palace",
      "name": "국립고궁박물원",
      "category": ["culture", "sightseeing", "family"],
      "budget_level": ["medium", "high"],
      "suitable_for": ["solo", "friend", "family", "couple"],
      "time_fit": ["morning", "afternoon"],
      "area": "스린",
      "duration_hours": 3,
      "priority": 9,
      "pace": ["easy"],
      "mobility": ["taxi-needed"],
      "summary": "문화 중심 일정에서 빠지기 어려운 대표 박물관이다."
    },
    {
      "id": "shilin-night-market",
      "name": "스린 야시장",
      "category": ["food", "shopping", "nightlife"],
      "budget_level": ["low", "medium"],
      "suitable_for": ["friend", "solo", "family", "couple"],
      "time_fit": ["evening"],
      "area": "스린",
      "duration_hours": 2,
      "priority": 8,
      "pace": ["easy", "tight"],
      "mobility": ["walkable", "subway-friendly"],
      "summary": "먹거리와 활기 있는 분위기를 좋아하면 만족도가 높은 야시장이다."
    }
  ]
}
